notenotice/__init__.py
notenotice-0.0.3.dist-info/LICENSE
notenotice-0.0.3.dist-info/METADATA
notenotice-0.0.3.dist-info/WHEEL
notenotice-0.0.3.dist-info/top_level.txt
notenotice-0.0.3.dist-info/RECORD
