Metadata-Version: 2.1
Name: notenotice
Version: 0.0.3
Summary: notenotice
Home-page: https://github.com/1007530194
Author: niult
Author-email: 1007530194@qq.com
License: UNKNOWN
Platform: UNKNOWN
Requires-Dist: wechatpy
